{
  "comments": {
    "data": [
      {
        "created_time": "2017-10-17T06:03:48+0000", 
        "from": {
          "id": "1832901180115687", 
          "name": "Ian Dorney"
        }, 
        "id": "1941737232759151", 
        "message": "728 13th Ave SE. Also, we're looking for someone to move in and replace Dave since he clearly doesn't value the house..."
      }
    ], 
    "paging": {
      "cursors": {
        "after": "WTI5dGJXVnVkRjlqZAFhKemIzSTZANVGswTVRjek56SXpNamMxT1RFMU1Ub3hOVEE0TWpJd01qSTQZD", 
        "before": "WTI5dGJXVnVkRjlqZAFhKemIzSTZANVGswTVRjek56SXpNamMxT1RFMU1Ub3hOVEE0TWpJd01qSTQZD"
      }
    }
  }, 
  "from": {
    "id": "1051875281621709", 
    "name": "David Ebben"
  }, 
  "id": "1573851542881057_1941671106099097", 
  "message": "Hello Cru! I realize that most of us have incredibly little free time because student-ing is hard, but if you would like to join the men of the embassy in worshiping and serving the Lord through prayer, there will be a weekly prayer meeting from 7:15-8 on Wednesday nights! The embassy's address is 728 13th ave SE", 
  "reactions": {
    "data": [
      {
        "id": "10102890032543851", 
        "name": "Angela Cooksey", 
        "type": "LIKE"
      }, 
      {
        "id": "10159754534395574", 
        "name": "Sam Xiong", 
        "type": "LIKE"
      }, 
      {
        "id": "1832901180115687", 
        "name": "Ian Dorney", 
        "type": "LIKE"
      }, 
      {
        "id": "1922774227750507", 
        "name": "Sarah Strandmark", 
        "type": "LIKE"
      }, 
      {
        "id": "10214791079794361", 
        "name": "Anna Hemze", 
        "type": "LIKE"
      }, 
      {
        "id": "1710378252326163", 
        "name": "Nick Anderson", 
        "type": "LIKE"
      }, 
      {
        "id": "1578492555567044", 
        "name": "Katelyn Schroeder", 
        "type": "LIKE"
      }, 
      {
        "id": "10215535507686157", 
        "name": "Amy Underwood", 
        "type": "LIKE"
      }, 
      {
        "id": "1316990971780613", 
        "name": "Chris Heen", 
        "type": "LIKE"
      }, 
      {
        "id": "10210307180308602", 
        "name": "Josh Holtz", 
        "type": "LOVE"
      }, 
      {
        "id": "510804585970190", 
        "name": "Collin Humpal", 
        "type": "LIKE"
      }, 
      {
        "id": "1533639273352268", 
        "name": "Curtis Zicker", 
        "type": "LIKE"
      }, 
      {
        "id": "1220166774749498", 
        "name": "Dakota Snustad", 
        "type": "LIKE"
      }, 
      {
        "id": "953460174812249", 
        "name": "John Sampson", 
        "type": "LIKE"
      }, 
      {
        "id": "1566873946711485", 
        "name": "Alyssa Burk", 
        "type": "LIKE"
      }, 
      {
        "id": "1607037739423373", 
        "name": "Julia Christine Asmus", 
        "type": "LIKE"
      }, 
      {
        "id": "1569995489747361", 
        "name": "Eric Hess", 
        "type": "LIKE"
      }, 
      {
        "id": "1809883889024656", 
        "name": "Connor Lund", 
        "type": "LOVE"
      }, 
      {
        "id": "10154964330996965", 
        "name": "Frank Hutton", 
        "type": "LIKE"
      }
    ], 
    "paging": {
      "cursors": {
        "after": "TlRBeE1EWXhPVFkwT2pFMU1EZA3lNRFUxTVRZANk1qVTBNRGsyTVRZAeE13PT0ZD", 
        "before": "TkRRd01URTJOamc2TVRVd09ETTBNalEzT1RveU5UUXdPVFl4TmpFegZDZD"
      }
    }
  }
}