{
  "comments": {
    "data": [
      {
        "created_time": "2016-07-27T04:40:45+0000", 
        "from": {
          "id": "2173505262675191", 
          "name": "Everett Tsang"
        }, 
        "id": "1734695070130036", 
        "message": "cped"
      }
    ], 
    "paging": {
      "cursors": {
        "after": "WTI5dGJXVnVkRjlqZAFhKemIzSTZANVGN6TkRZANU5UQTNNREV6TURBek5qb3hORFk1TlRrME5EUTEZD", 
        "before": "WTI5dGJXVnVkRjlqZAFhKemIzSTZANVGN6TkRZANU5UQTNNREV6TURBek5qb3hORFk1TlRrME5EUTEZD"
      }
    }
  }, 
  "from": {
    "id": "1982288902036529", 
    "name": "Emily Wydo"
  }, 
  "id": "1573851542881057_1734694993463377", 
  "message": "Hello all!\nFor anyone who is still awake or let's me know before 6:30 am tomorrow\nI am going to Hope Community to join in praying for our city/world from 7-8 am or so.\nI can pick you up if you are on campus!\nLet me know!", 
  "reactions": {
    "data": [
      {
        "id": "10215251311658361", 
        "name": "Ashlinn Thommes", 
        "type": "LIKE"
      }, 
      {
        "id": "1528520517184890", 
        "name": "Annie Harwell", 
        "type": "LIKE"
      }, 
      {
        "id": "10215175597290322", 
        "name": "Aaron Shaw", 
        "type": "LIKE"
      }, 
      {
        "id": "10214532454047747", 
        "name": "Javier Bowen", 
        "type": "LIKE"
      }, 
      {
        "id": "1708303689221509", 
        "name": "Jenifer Smith", 
        "type": "LIKE"
      }, 
      {
        "id": "1578492555567044", 
        "name": "Katelyn Schroeder", 
        "type": "LIKE"
      }
    ], 
    "paging": {
      "cursors": {
        "after": "TVRBd01EQXlNVGc1TkRNNE5qY3pPakUwTmprMU9UVXdOakE2TWpVME1EazJNVFl4TXc9PQZDZD", 
        "before": "TVRNd01USTNNamMzTnpveE5EWTVOak13TnpreU9qSTFOREE1TmpFMk1UTT0ZD"
      }
    }
  }
}