{
  "comments": {
    "data": [
      {
        "created_time": "2016-10-18T01:16:07+0000", 
        "from": {
          "id": "10208514289294470", 
          "name": "Chelsea Spencer"
        }, 
        "id": "1770328869899989", 
        "message": "Wow that was literally the easiest thing I've ever done. Breathing is harder even."
      }
    ], 
    "paging": {
      "cursors": {
        "after": "WTI5dGJXVnVkRjlqZAFhKemIzSTZANVGMzTURNeU9EZAzJPVGc1T1RrNE9Ub3hORGMyTnpVek16WTMZD", 
        "before": "WTI5dGJXVnVkRjlqZAFhKemIzSTZANVGMzTURNeU9EZAzJPVGc1T1RrNE9Ub3hORGMyTnpVek16WTMZD"
      }
    }
  }, 
  "from": {
    "id": "1590799184292470", 
    "name": "Amy Yi"
  }, 
  "id": "1573851542881057_1770323669900509", 
  "message": "Hey guys! I have a stats project that I need data for, and I was wondering if you guys could help me out! It literally takes less than 2 minutes and it's completely anonymous! Thank you all so much! ", 
  "reactions": {
    "data": [
      {
        "id": "1555068064579191", 
        "name": "Katherine Myers", 
        "type": "LIKE"
      }, 
      {
        "id": "10214532454047747", 
        "name": "Javier Bowen", 
        "type": "LIKE"
      }, 
      {
        "id": "1297152383724306", 
        "name": "Jessica Rislove", 
        "type": "LIKE"
      }
    ], 
    "paging": {
      "cursors": {
        "after": "TVRBd01EQXlPRGcyTnpFek5EY3dPakUwTnpZAM05USXlOelE2TWpVME1EazJNVFl4TXc9PQZDZD", 
        "before": "TVRBd01EQXlNamd3TXpZAeE9UWXhPakUwTnpZAM05UWTNOelE2TWpVME1EazJNVFl4TXc9PQZDZD"
      }
    }
  }
}