{
  "from": {
    "id": "1694792690572124", 
    "name": "Amy Olsen"
  }, 
  "id": "1573851542881057_1765004583765751", 
  "message": "PSA:\nToday's the last day to get the cheaper rate for Fall Retreat!! After midnight prices are going up by $25 (or 5 Starbucks drinks, depending on how you look at it..) so make sure you are signing up!! If you have already: kudos!! If you haven't: do it NOW! Remember to get your checks in the mail today as well if that's your mode of payment.\n\nHere's the link to sign up:\nhttp://www.twincitiescru.com/opportunities/fallretreat/\n\nT-8 days till we hit the road to good ole Osceola!!!", 
  "reactions": {
    "data": [
      {
        "id": "10210164788188609", 
        "name": "Mackenzie Darling", 
        "type": "LIKE"
      }, 
      {
        "id": "1758671560810357", 
        "name": "Jacque Lacy", 
        "type": "LIKE"
      }, 
      {
        "id": "1685824318145672", 
        "name": "Krista Keranen", 
        "type": "LIKE"
      }, 
      {
        "id": "10155316565428237", 
        "name": "Autumn Beckman", 
        "type": "LIKE"
      }, 
      {
        "id": "1590799184292470", 
        "name": "Amy Yi", 
        "type": "LIKE"
      }, 
      {
        "id": "915660251916466", 
        "name": "Micaela Schneider", 
        "type": "LIKE"
      }, 
      {
        "id": "1698716843482852", 
        "name": "Josie Jones", 
        "type": "LIKE"
      }, 
      {
        "id": "10215428465094757", 
        "name": "Michael Francis", 
        "type": "LIKE"
      }, 
      {
        "id": "1949407998407215", 
        "name": "Steph Shiro", 
        "type": "LIKE"
      }, 
      {
        "id": "1681439038583153", 
        "name": "Lauren Otto", 
        "type": "LIKE"
      }, 
      {
        "id": "1982288902036529", 
        "name": "Emily Wydo", 
        "type": "LIKE"
      }, 
      {
        "id": "1748552338788069", 
        "name": "David Deming", 
        "type": "LIKE"
      }, 
      {
        "id": "1555068064579191", 
        "name": "Katherine Myers", 
        "type": "LIKE"
      }, 
      {
        "id": "1969880233036990", 
        "name": "Jason Adlam", 
        "type": "LIKE"
      }, 
      {
        "id": "1516058458479574", 
        "name": "Kallie Erickson", 
        "type": "LIKE"
      }, 
      {
        "id": "10215535507686157", 
        "name": "Amy Underwood", 
        "type": "LIKE"
      }, 
      {
        "id": "10213457272737717", 
        "name": "Erik Tungland", 
        "type": "LIKE"
      }, 
      {
        "id": "1710378252326163", 
        "name": "Nick Anderson", 
        "type": "LIKE"
      }, 
      {
        "id": "10213695757206861", 
        "name": "Chaz Fenske", 
        "type": "LIKE"
      }
    ], 
    "paging": {
      "cursors": {
        "after": "TVRFNU1qazBNRFE0TWpveE5EYzFOemd3TWpjek9qSTFOREE1TmpFMk1UTT0ZD", 
        "before": "TVRZAd05Ua3pNemczTlRveE5EYzFPREV4TVRJd09qSTFOREE1TmpFMk1UTT0ZD"
      }
    }
  }
}