{
  "comments": {
    "data": [
      {
        "created_time": "2016-05-12T02:00:21+0000", 
        "from": {
          "id": "1982288902036529", 
          "name": "Emily Wydo"
        }, 
        "id": "1703843379881872", 
        "message": "<3 you"
      }, 
      {
        "created_time": "2016-05-12T02:06:22+0000", 
        "from": {
          "id": "1991513320875521", 
          "name": "Emily Magnuson"
        }, 
        "id": "1703844999881710", 
        "message": "back atchya! <3"
      }
    ], 
    "paging": {
      "cursors": {
        "after": "WTI5dGJXVnVkRjlqZAFhKemIzSTZANVGN3TXpnME5EazVPVGc0TVRjeE1Eb3hORFl6TURFNE56ZA3kZD", 
        "before": "WTI5dGJXVnVkRjlqZAFhKemIzSTZANVGN3TXpnME16TTNPVGc0TVRnM01qb3hORFl6TURFNE5ESXkZD"
      }
    }
  }, 
  "from": {
    "id": "1991513320875521", 
    "name": "Emily Magnuson"
  }, 
  "id": "1573851542881057_1703843209881889", 
  "message": "Me:", 
  "reactions": {
    "data": [
      {
        "id": "10210910847632864", 
        "name": "Sammi Pavett", 
        "type": "LIKE"
      }, 
      {
        "id": "10208151570346232", 
        "name": "Jon Burns", 
        "type": "HAHA"
      }, 
      {
        "id": "10213217453089024", 
        "name": "Josh Bartelme", 
        "type": "LIKE"
      }, 
      {
        "id": "1681439038583153", 
        "name": "Lauren Otto", 
        "type": "LIKE"
      }, 
      {
        "id": "1568481316531583", 
        "name": "Paige Hildebrandt", 
        "type": "LIKE"
      }, 
      {
        "id": "10159692032995134", 
        "name": "Brandon Roiger", 
        "type": "LIKE"
      }, 
      {
        "id": "1698995160144583", 
        "name": "Croix Menzel", 
        "type": "LIKE"
      }, 
      {
        "id": "1768598043152636", 
        "name": "Emma Schwartz", 
        "type": "LIKE"
      }, 
      {
        "id": "1971554446428903", 
        "name": "Tommy Doherty", 
        "type": "LIKE"
      }, 
      {
        "id": "10213532794941755", 
        "name": "Mattie Park", 
        "type": "LIKE"
      }, 
      {
        "id": "2213109262036813", 
        "name": "Carter Blum", 
        "type": "LIKE"
      }, 
      {
        "id": "10215182017928851", 
        "name": "Lydia Holmes", 
        "type": "LIKE"
      }, 
      {
        "id": "10215581304751715", 
        "name": "David Nelson", 
        "type": "LIKE"
      }, 
      {
        "id": "1686449131405584", 
        "name": "Olivia Johnson", 
        "type": "LIKE"
      }, 
      {
        "id": "1710090652356064", 
        "name": "Tayne Andersen", 
        "type": "LIKE"
      }, 
      {
        "id": "1645707085489633", 
        "name": "Krista Hamann", 
        "type": "LIKE"
      }, 
      {
        "id": "1887238894623983", 
        "name": "Grant Kregness", 
        "type": "LIKE"
      }, 
      {
        "id": "1922774227750507", 
        "name": "Sarah Strandmark", 
        "type": "LIKE"
      }, 
      {
        "id": "1578492555567044", 
        "name": "Katelyn Schroeder", 
        "type": "LIKE"
      }, 
      {
        "id": "10203859786810345", 
        "name": "Lucy Bixby", 
        "type": "LIKE"
      }, 
      {
        "id": "1710378252326163", 
        "name": "Nick Anderson", 
        "type": "LIKE"
      }, 
      {
        "id": "10210766752821908", 
        "name": "Anna Oliver", 
        "type": "LIKE"
      }, 
      {
        "id": "10211549457035989", 
        "name": "Abbie Homan", 
        "type": "LIKE"
      }, 
      {
        "id": "1694792690572124", 
        "name": "Amy Olsen", 
        "type": "LIKE"
      }, 
      {
        "id": "1758671560810357", 
        "name": "Jacque Lacy", 
        "type": "LIKE"
      }, 
      {
        "id": "10212515445034913", 
        "name": "Bri Schmitt", 
        "type": "LIKE"
      }, 
      {
        "id": "1982288902036529", 
        "name": "Emily Wydo", 
        "type": "LIKE"
      }, 
      {
        "id": "10211015765453616", 
        "name": "Molly Senser", 
        "type": "LIKE"
      }
    ], 
    "paging": {
      "cursors": {
        "after": "TVRNek9URTFPRFkxTXpveE5EWXpNREU0TXpZAMk9qSTFOREE1TmpFMk1UTT0ZD", 
        "before": "TVRRd01qazRPRGM0T0RveE5EWXpNVFkwTkRZANE9qSTFOREE1TmpFMk1UTT0ZD"
      }
    }
  }
}