{
  "comments": {
    "data": [
      {
        "created_time": "2017-03-24T19:40:55+0000", 
        "from": {
          "id": "10213695757206861", 
          "name": "Chaz Fenske"
        }, 
        "id": "1844990639100478", 
        "message": "Chuck is en route"
      }
    ], 
    "paging": {
      "cursors": {
        "after": "WTI5dGJXVnVkRjlqZAFhKemIzSTZANVGcwTkRrNU1EWXpPVEV3TURRM09Eb3hORGt3TXpnME5EVTIZD", 
        "before": "WTI5dGJXVnVkRjlqZAFhKemIzSTZANVGcwTkRrNU1EWXpPVEV3TURRM09Eb3hORGt3TXpnME5EVTIZD"
      }
    }
  }, 
  "from": {
    "id": "1533639273352268", 
    "name": "Curtis Zicker"
  }, 
  "id": "1573851542881057_1844862375779971", 
  "message": "Hey friends! Katherine Myers and I will be sharing in Coffman at 3 today at the top of the escalators. We'd love to see you all there, have a wonderful Friday!", 
  "reactions": {
    "data": [
      {
        "id": "2173505262675191", 
        "name": "Everett Tsang", 
        "type": "LIKE"
      }, 
      {
        "id": "10213695757206861", 
        "name": "Chaz Fenske", 
        "type": "LIKE"
      }, 
      {
        "id": "1685824318145672", 
        "name": "Krista Keranen", 
        "type": "LIKE"
      }, 
      {
        "id": "1740903819295617", 
        "name": "Kc Butorac", 
        "type": "LIKE"
      }, 
      {
        "id": "1710378252326163", 
        "name": "Nick Anderson", 
        "type": "LIKE"
      }, 
      {
        "id": "2160758780814425", 
        "name": "Josh Lassen", 
        "type": "LIKE"
      }, 
      {
        "id": "1555068064579191", 
        "name": "Katherine Myers", 
        "type": "LIKE"
      }, 
      {
        "id": "10155316565428237", 
        "name": "Autumn Beckman", 
        "type": "LOVE"
      }, 
      {
        "id": "1922774227750507", 
        "name": "Sarah Strandmark", 
        "type": "LIKE"
      }, 
      {
        "id": "1971554446428903", 
        "name": "Tommy Doherty", 
        "type": "LIKE"
      }, 
      {
        "id": "510804585970190", 
        "name": "Collin Humpal", 
        "type": "LIKE"
      }, 
      {
        "id": "10214541165742552", 
        "name": "John Ke", 
        "type": "LIKE"
      }, 
      {
        "id": "1564345963660661", 
        "name": "Matthew Edgar", 
        "type": "LIKE"
      }
    ], 
    "paging": {
      "cursors": {
        "after": "TVRBd01EQXlOVFU0TVRnMk9EVXdPakUwT1RBek5qYzFNRGs2TWpVME1EazJNVFl4TXc9PQZDZD", 
        "before": "TVRBd01EQXdORGN5TVRVME5qQTNPakUwT1RBME1EQTRORGM2TWpVME1EazJNVFl4TXc9PQZDZD"
      }
    }
  }
}