{
  "from": {
    "id": "10210589201029116", 
    "name": "Andrea Meitler"
  }, 
  "id": "1573851542881057_1638682513064626", 
  "message": "International Justice Mission UMN is having a Coffee Hour tomorrow morning at 11am in Folwell Rm 120. Join us for some caffeine and justice-seeking community!", 
  "reactions": {
    "data": [
      {
        "id": "10214791079794361", 
        "name": "Anna Hemze", 
        "type": "LIKE"
      }, 
      {
        "id": "10156143552337845", 
        "name": "Taylor Woodall", 
        "type": "LIKE"
      }, 
      {
        "id": "1922774227750507", 
        "name": "Sarah Strandmark", 
        "type": "LIKE"
      }, 
      {
        "id": "10212960191814379", 
        "name": "Rachel Joy Abercrombie", 
        "type": "LIKE"
      }, 
      {
        "id": "10212733447989285", 
        "name": "Matt Almquist", 
        "type": "LIKE"
      }, 
      {
        "id": "1805372482808856", 
        "name": "Bethany Schluter", 
        "type": "LIKE"
      }
    ], 
    "paging": {
      "cursors": {
        "after": "TVRBd01EQXdNRGd6TmpVeU9Ua3lPakUwTkRZANE5EQTRPRGM2TWpVME1EazJNVFl4TXc9PQZDZD", 
        "before": "TVRNME5qVXlNak0yT1RveE5EUTJPRFEwTmpNMk9qSTFOREE1TmpFMk1UTT0ZD"
      }
    }
  }
}