{
  "comments": {
    "data": [
      {
        "created_time": "2017-04-26T01:32:11+0000", 
        "from": {
          "id": "1578492555567044", 
          "name": "Katelyn Schroeder"
        }, 
        "id": "1861633107436231", 
        "message": "Rae Young"
      }, 
      {
        "created_time": "2017-04-26T01:43:22+0000", 
        "from": {
          "id": "1558266234253442", 
          "name": "Gabe Kaufmann"
        }, 
        "id": "1861635530769322", 
        "message": "Nick Anderson"
      }
    ], 
    "paging": {
      "cursors": {
        "after": "WTI5dGJXVnVkRjlqZAFhKemIzSTZANVGcyTVRZAek5UVXpNRGMyT1RNeU1qb3hORGt6TVRjeE1EQXkZD", 
        "before": "WTI5dGJXVnVkRjlqZAFhKemIzSTZANVGcyTVRZAek16RXdOelF6TmpJek1Ub3hORGt6TVRjd016TXkZD"
      }
    }
  }, 
  "from": {
    "id": "915660251916466", 
    "name": "Micaela Schneider"
  }, 
  "id": "1573851542881057_1861616030771272", 
  "message": "Hi Everyone! The Mosaic has an opening for next year (fall and spring)! You'll share a room and rent is around $420 and if you're trying to move in early we'll definitely be able to accommodate! Message me if interested!", 
  "reactions": {
    "data": [
      {
        "id": "1559313610842902", 
        "name": "Makayla Hansen", 
        "type": "LIKE"
      }, 
      {
        "id": "10213123261590458", 
        "name": "Ellie Bauer", 
        "type": "LIKE"
      }, 
      {
        "id": "10210693817118409", 
        "name": "Amber Koehnen", 
        "type": "LIKE"
      }, 
      {
        "id": "1645707085489633", 
        "name": "Krista Hamann", 
        "type": "LIKE"
      }, 
      {
        "id": "1694792690572124", 
        "name": "Amy Olsen", 
        "type": "LIKE"
      }, 
      {
        "id": "1802845369788501", 
        "name": "Maddie Causey", 
        "type": "LIKE"
      }
    ], 
    "paging": {
      "cursors": {
        "after": "TVRBd01EQXhPRGt4TmpVMk5qWTJPakUwT1RNeE5qWTJOVE02TWpVME1EazJNVFl4TXc9PQZDZD", 
        "before": "TVRBd01EQXlPVEk0TXpReE5UQXdPakUwT1RNeU5qQXdNalU2TWpVME1EazJNVFl4TXc9PQZDZD"
      }
    }
  }
}