{
  "from": {
    "id": "10215407946097423", 
    "name": "Suzanne Bush-Haruna"
  }, 
  "id": "1573851542881057_1645188039080740", 
  "message": "Hey people of Cru! I am looking for housing with other Christians for next spring semester, and possibly during the summer that is under $400 per month (including utilities, etc). I will be graduating this Fall, but will be working somewhat around the U. Let me know if you are subleasing or know someone who has an open spot!", 
  "reactions": {
    "data": [
      {
        "id": "10159723812655430", 
        "name": "Stephanie C. Farenik", 
        "type": "LIKE"
      }
    ], 
    "paging": {
      "cursors": {
        "after": "TmpjNU16RXdOREk1T2pFME5Ea3hNVFV3TnpjNk1qVTBNRGsyTVRZAeE13PT0ZD", 
        "before": "TmpjNU16RXdOREk1T2pFME5Ea3hNVFV3TnpjNk1qVTBNRGsyTVRZAeE13PT0ZD"
      }
    }
  }
}